sigalign-0.3.1.dist-info/METADATA
sigalign-0.3.1.dist-info/WHEEL
sigalign/__init__.py
sigalign/sigalign.abi3.so
sigalign-0.3.1.dist-info/RECORD
