Metadata-Version: 2.3
Name: sigalign
Version: 0.3.1
Classifier: License :: OSI Approved :: MIT License
Classifier: Programming Language :: Rust
Classifier: Programming Language :: Python
Classifier: Programming Language :: Python :: Implementation :: CPython
Classifier: Programming Language :: Python :: Implementation :: PyPy
Classifier: Operating System :: POSIX
Classifier: Operating System :: MacOS :: MacOS X
Classifier: Operating System :: Microsoft :: Windows
Summary: SigAlign's language binding for python
Author: baku
Author-email: baku4 <bahkhun@gmail.com>
Requires-Python: >=3.10
Project-URL: Repository, https://github.com/baku4/sigalign
